AUTHORS
CHANGELOG.txt
DESCRIPTION
LICENSE
MANIFEST.in
README.rst
setup.cfg
setup.py
alogator/__init__.py
alogator/admin.py
alogator/alogator_cli
alogator/logwatch.py
alogator/models.py
alogator/urls.py
alogator/views.py
alogator.egg-info/PKG-INFO
alogator.egg-info/SOURCES.txt
alogator.egg-info/dependency_links.txt
alogator.egg-info/requires.txt
alogator.egg-info/top_level.txt
alogator/management/__init__.py
alogator/management/commands/__init__.py
alogator/management/commands/scanlogfiles.py
alogator/migrations/0001_initial.py
alogator/migrations/0002_auto_20150520_1106.py
alogator/migrations/0003_auto_20150520_1424.py
alogator/migrations/__init__.py
alogator/static/.empty
alogator/static/alogator/.empty
alogator/templates/alogator/.empty
alogator/templates/alogator/email/pattern_found.txt
alogator/templates/alogator/email/slack_message.txt
alogator/templatetags/__init__.py
alogator/templatetags/alogator_tags.py
alogator/tests/__init__.py
alogator/tests/factories.py
alogator/tests/models_tests.py
alogator/tests/runtests.py
alogator/tests/south_settings.py
alogator/tests/test_settings.py
alogator/tests/urls.py
alogator/tests/test_app/__init__.py
alogator/tests/test_app/models.py
alogator/tests/test_app/templates/400.html
alogator/tests/test_app/templates/500.html