Metadata-Version: 1.1
Name: alogator
Version: 0.2.0
Summary: Alogator is an aggregated logging actor system.
